ciscoconfparse2/__about__.py
ciscoconfparse2/__init__.py
ciscoconfparse2/__main__.py
ciscoconfparse2/ccp_abc.py
ciscoconfparse2/ccp_util.py
ciscoconfparse2/ciscoconfparse2.py
ciscoconfparse2/cli_script.py
ciscoconfparse2/errors.py
ciscoconfparse2/models_asa.py
ciscoconfparse2/models_base.py
ciscoconfparse2/models_cisco.py
ciscoconfparse2/models_iosxr.py
ciscoconfparse2/models_junos.py
ciscoconfparse2/models_nxos.py
ciscoconfparse2/protocol_values.py
tests/conftest.py
tests/test_BraceParse.py
tests/test_Ccp_Abc.py
tests/test_Ccp_Util.py
tests/test_CiscoConfParse.py
tests/test_Cli_Script.py
tests/test_Models_Asa.py
tests/test_Models_Cisco.py
tests/test_Models_Junos.py
tests/fixtures/configs/HP_Procurve.conf
tests/fixtures/configs/build_big_config.py
tests/fixtures/configs/sample_01.asa
tests/fixtures/configs/sample_01.catos
tests/fixtures/configs/sample_01.f5
tests/fixtures/configs/sample_01.ios
tests/fixtures/configs/sample_01.iosxr
tests/fixtures/configs/sample_01.junos
tests/fixtures/configs/sample_01.nxos
tests/fixtures/configs/sample_02.f5
tests/fixtures/configs/sample_02.ios
tests/fixtures/configs/sample_02.iosxr
tests/fixtures/configs/sample_02.junos
tests/fixtures/configs/sample_03.f5
tests/fixtures/configs/sample_03.ios
tests/fixtures/configs/sample_03.iosxr
tests/fixtures/configs/sample_03.junos
tests/fixtures/configs/sample_04.ios
tests/fixtures/configs/sample_04.iosxr
tests/fixtures/configs/sample_04.junos
tests/fixtures/configs/sample_05.ios
tests/fixtures/configs/sample_05.iosxr
tests/fixtures/configs/sample_06.ios
tests/fixtures/configs/sample_06.iosxr
tests/fixtures/configs/sample_07.ios
tests/fixtures/configs/sample_07.iosxr
tests/fixtures/configs/sample_08.ios
tests/fixtures/configs/sample_09.ios
tests/fixtures/configs/sample_10.ios
tests/fixtures/plain_text/sample_01.txt
ciscoconfparse2-0.9.7.dist-info/METADATA
ciscoconfparse2-0.9.7.dist-info/WHEEL
ciscoconfparse2-0.9.7.dist-info/entry_points.txt
ciscoconfparse2-0.9.7.dist-info/licenses/LICENSE
ciscoconfparse2-0.9.7.dist-info/RECORD
