Metadata-Version: 2.4
Name: ciscoconfparse2
Version: 0.9.7
Summary: Parse, Audit, Query, Build, and Modify Cisco IOS-style and JunOS-style configs
Project-URL: homepage, http://github.com/mpenning/ciscoconfparse2
Project-URL: changelog, https://github.com/mpenning/ciscoconfparse2/blob/main/CHANGES.md
Project-URL: repository, https://github.com/mpenning/ciscoconfparse2
Project-URL: documentation, http://www.pennington.net/py/ciscoconfparse2/
Author-email: Mike Pennington <mike@pennington.net>
License-Expression: GPL-3.0-only
License-File: LICENSE
Keywords: ASA,Cisco,Cisco IOS,Juniper,NXOS,Parse,audit,modify,query
Classifier: Development Status :: 5 - Production/Stable
Classifier: Environment :: Plugins
Classifier: Intended Audience :: Developers
Classifier: Intended Audience :: Information Technology
Classifier: Intended Audience :: System Administrators
Classifier: Intended Audience :: Telecommunications Industry
Classifier: License :: OSI Approved :: GNU General Public License (GPL)
Classifier: License :: OSI Approved :: GNU General Public License v3 (GPLv3)
Classifier: Natural Language :: English
Classifier: Operating System :: OS Independent
Classifier: Programming Language :: Python
Classifier: Topic :: Communications
Classifier: Topic :: Internet
Classifier: Topic :: System :: Networking
Classifier: Topic :: System :: Networking :: Monitoring
Requires-Python: >=3.10
Requires-Dist: attrs<26.0.0,>24.3.0
Requires-Dist: dnspython==2.8.0
Requires-Dist: hier-config==2.3.1
Requires-Dist: hypothesis==6.150.3
Requires-Dist: libpass==1.9.3
Requires-Dist: loguru>=0.7.2
Requires-Dist: macaddress==2.0.2
Requires-Dist: pyparsing==3.3.2
Requires-Dist: pyyaml>=6.0.2
Requires-Dist: rich>=14.3.0
Requires-Dist: toml==0.10.2
Requires-Dist: traitlets==5.14.3
Requires-Dist: typeguard==4.4.4
Provides-Extra: dev
Requires-Dist: black==25.11.0; extra == 'dev'
Requires-Dist: commitizen>=2.40.0; extra == 'dev'
Requires-Dist: coverage>=7.3.2; extra == 'dev'
Requires-Dist: fabric==3.2.2; extra == 'dev'
Requires-Dist: hatch>=1.16.3; extra == 'dev'
Requires-Dist: hatchling>=1.28.0; extra == 'dev'
Requires-Dist: invoke==2.2.1; extra == 'dev'
Requires-Dist: pre-commit>=4.3.0; extra == 'dev'
Requires-Dist: pylama==8.4.1; extra == 'dev'
Requires-Dist: pylint==4.0.4; extra == 'dev'
Requires-Dist: pyroma==5.0.1; extra == 'dev'
Requires-Dist: pytest-cov>=4.1.0; extra == 'dev'
Requires-Dist: pytest>=9.0.1; extra == 'dev'
Requires-Dist: python-lsp-server>=1.12.2; extra == 'dev'
Requires-Dist: pyupgrade==3.21.2; extra == 'dev'
Requires-Dist: tox==4.30.3; extra == 'dev'
Requires-Dist: ty==0.0.13; extra == 'dev'
Requires-Dist: yamlfix==1.19.1; extra == 'dev'
Provides-Extra: doc
Requires-Dist: numpydoc==1.9.0; extra == 'doc'
Requires-Dist: pydocstyle==6.3.0; extra == 'doc'
Requires-Dist: sphinx-rtd-theme>=2.0.0; extra == 'doc'
Requires-Dist: sphinx>=9.0.4; extra == 'doc'
